setup.py
weekdayofdate/__init__.py
weekdayofdate/weekdayofdate.py
weekdayofdate.egg-info/PKG-INFO
weekdayofdate.egg-info/SOURCES.txt
weekdayofdate.egg-info/dependency_links.txt
weekdayofdate.egg-info/top_level.txt