Metadata-Version: 1.0
Name: weekdayofdate
Version: 1.0
Summary: calculate the weekday of a date
Home-page: https://github.com/RafaelRodriguezLara/Guess-the-weekday-of-a-date
Author: Rafael Rodriguez
Author-email: UNKNOWN
License: UNKNOWN
Platform: UNKNOWN
